soco_trainer_plugin
